MANIFEST.in
setup.py
tox.ini
api_object_schema/__init__.py
api_object_schema/__version__.py
api_object_schema/_compat.py
api_object_schema/binding.py
api_object_schema/field.py
api_object_schema/fields.py
api_object_schema/special_value.py
api_object_schema/type_info.py
api_object_schema/utils.py
api_object_schema/value_translator.py
api_object_schema.egg-info/PKG-INFO
api_object_schema.egg-info/SOURCES.txt
api_object_schema.egg-info/dependency_links.txt
api_object_schema.egg-info/namespace_packages.txt
api_object_schema.egg-info/requires.txt
api_object_schema.egg-info/top_level.txt
tests/__init__.py
tests/test_binding.py
tests/test_binding_translation.py
tests/test_fields.py
tests/test_type_info.py
tests/test_utils.py