Metadata-Version: 1.1
Name: api-object-schema
Version: 2.0.0
Summary: Utilities for defining schemas of Pythonic objects interacting with external APIs
Home-page: https://github.com/Infinidat/api_object_schema
Author: Infinidat Ltd.
Author-email: info@infinidat.com
License: BSD3
Platform: UNKNOWN
Classifier: Programming Language :: Python :: 2.7
Classifier: Programming Language :: Python :: 3.5
Classifier: Programming Language :: Python :: 3.6
